crypto_empyrical/__init__.py
crypto_empyrical/_version.py
crypto_empyrical/deprecate.py
crypto_empyrical/perf_attrib.py
crypto_empyrical/periods.py
crypto_empyrical/stats.py
crypto_empyrical/utils.py
crypto_empyrical/tests/__init__.py
crypto_empyrical/tests/test_perf_attrib.py
crypto_empyrical/tests/test_stats.py
crypto_empyrical-1.0.4.dist-info/LICENSE
crypto_empyrical-1.0.4.dist-info/METADATA
crypto_empyrical-1.0.4.dist-info/WHEEL
crypto_empyrical-1.0.4.dist-info/top_level.txt
crypto_empyrical-1.0.4.dist-info/RECORD
